testumbrella/__init__.py
testumbrella/main.py
testumbrella/.system/imports.py
testumbrella/.system/index.py
testumbrella/.system/modules/jobs.py
testumbrella/.system/sources/clight.json
testumbrella/.system/sources/logo.ico
testumbrella-1.1.0.dist-info/METADATA
testumbrella-1.1.0.dist-info/WHEEL
testumbrella-1.1.0.dist-info/entry_points.txt
testumbrella-1.1.0.dist-info/top_level.txt
testumbrella-1.1.0.dist-info/RECORD
