Metadata-Version: 2.4
Name: testumbrella
Version: 1.1.0
Summary: Test umbrella project
Home-page: 
Author: Irakli Gzirishvili
Author-email: gziraklirex@gmail.com
Classifier: Programming Language :: Python :: 3
Classifier: Operating System :: OS Independent
Requires-Dist: clight
Requires-Dist: testufirst==1.1.5
Requires-Dist: testusecond==1.0.4
Requires-Dist: testuthird==1.0.2
Requires-Dist: testufirst
Dynamic: author
Dynamic: author-email
Dynamic: classifier
Dynamic: description
Dynamic: description-content-type
Dynamic: requires-dist
Dynamic: summary
